client/__init__.py
client/client_part.py
client/client/__init__.py
client/client/add_contact.py
client/client/database.py
client/client/del_contact.py
client/client/main_window.py
client/client/main_window_conv.py
client/client/start_dialog.py
client/client/transport.py
client/general/__init__.py
client/general/decos.py
client/general/descriptors.py
client/general/errors.py
client/general/metaclasses.py
client/general/utils.py
client/general/variables.py
client/log/__init__.py
client/log/client_log_config.py
client/log/server_log_config.py
mess_system_client-0.1.0.dist-info/METADATA
mess_system_client-0.1.0.dist-info/WHEEL
mess_system_client-0.1.0.dist-info/top_level.txt
mess_system_client-0.1.0.dist-info/RECORD
